Calculator/__init__.py
akash_basic_calculator-0.0.1.dist-info/LICENSE.txt
akash_basic_calculator-0.0.1.dist-info/METADATA
akash_basic_calculator-0.0.1.dist-info/WHEEL
akash_basic_calculator-0.0.1.dist-info/top_level.txt
akash_basic_calculator-0.0.1.dist-info/RECORD
